thop/__init__.py
thop/fx_profile.py
thop/profile.py
thop/rnn_hooks.py
thop/utils.py
thop/vision/__init__.py
thop/vision/basic_hooks.py
thop/vision/calc_func.py
ultralytics_thop-2.0.7.dist-info/LICENSE
ultralytics_thop-2.0.7.dist-info/METADATA
ultralytics_thop-2.0.7.dist-info/WHEEL
ultralytics_thop-2.0.7.dist-info/top_level.txt
ultralytics_thop-2.0.7.dist-info/RECORD
